mtls_pluggable/__init__.py
mtls_pluggable/crypto.py
mtls_pluggable/frames.py
mtls_pluggable/handshake.py
mtls_pluggable/pki.py
mtls_pluggable-0.1.0.dist-info/licenses/LICENSE
mtls_pluggable-0.1.0.dist-info/METADATA
mtls_pluggable-0.1.0.dist-info/WHEEL
mtls_pluggable-0.1.0.dist-info/top_level.txt
mtls_pluggable-0.1.0.dist-info/RECORD
