Metadata-Version: 2.4
Name: mtls-pluggable
Version: 0.1.0
Summary: A pluggable mutual TLS (mTLS) library with PKI, crypto, and handshake utilities.
Author: Vishal Kumar
Author-email: Vishal Kumar <2003.v.vishal@gmail.com>
License: MIT License
Project-URL: Homepage, https://github.com/3002vishal/MTLS_Pluggable
Keywords: mtls,pki,security,tls,authentication
Requires-Python: >=3.8
License-File: LICENSE
Requires-Dist: cryptography>=42.0.0
Dynamic: license-file
